README.md
setup.py
rl_benchmark/__init__.py
rl_benchmark/util.py
rl_benchmark/version.py
rl_benchmark.egg-info/PKG-INFO
rl_benchmark.egg-info/SOURCES.txt
rl_benchmark.egg-info/dependency_links.txt
rl_benchmark.egg-info/not-zip-safe
rl_benchmark.egg-info/requires.txt
rl_benchmark.egg-info/top_level.txt
rl_benchmark/analyze/__init__.py
rl_benchmark/analyze/summary.py
rl_benchmark/analyze/transform.py
rl_benchmark/analyze/plotter/__init__.py
rl_benchmark/analyze/plotter/result_plotter.py
rl_benchmark/benchmark/__init__.py
rl_benchmark/benchmark/runner/__init__.py
rl_benchmark/benchmark/runner/benchmark_runner.py
rl_benchmark/benchmark/wrapper/__init__.py
rl_benchmark/benchmark/wrapper/environment_wrapper.py
rl_benchmark/benchmark/wrapper/results_wrapper.py
rl_benchmark/cli/__init__.py
rl_benchmark/cli/command.py
rl_benchmark/cli/util.py
rl_benchmark/cli/db/__init__.py
rl_benchmark/cli/db/create_config.py
rl_benchmark/cli/db/get.py
rl_benchmark/cli/db/info.py
rl_benchmark/cli/db/save.py
rl_benchmark/data/__init__.py
rl_benchmark/data/benchmark_data.py
rl_benchmark/data/experiment_data.py
rl_benchmark/db/__init__.py
rl_benchmark/db/cache.py
rl_benchmark/db/db.py
rl_benchmark/db/local_db.py
rl_benchmark/db/web_db.py
rl_benchmark/libraries/__init__.py
rl_benchmark/libraries/rlgraph.py
rl_benchmark/libraries/tensorforce.py