Metadata-Version: 1.0
Name: rl-benchmark
Version: 0.0.4
Summary: Reinforcement learning benchmarking package
Home-page: http://github.com/rlgraph/rl-benchmark
Author: RLgraph
Author-email: dev@rlgraph.org
License: Apache 2.0
Platform: UNKNOWN
